autoflex/__init__.py
autoflex/core/__init__.py
autoflex/core/actions.py
autoflex/core/config_loader.py
autoflex/core/exceptions.py
autoflex/core/logger.py
autoflex/core/web_manager.py
autoflex/tests/__init__.py
autoflex/tests/test_browser.py
autoflex-1.0.0.dist-info/METADATA
autoflex-1.0.0.dist-info/WHEEL
autoflex-1.0.0.dist-info/top_level.txt
autoflex-1.0.0.dist-info/RECORD
