Metadata-Version: 2.4
Name: autoflex
Version: 1.0.0
Summary: Web and System Automation Testing Framework
Home-page: https://github.com/LZYEIL/AutoFlex
Author: Zhiyuan Li
Author-email: zhiyuanjeremy@gmail.com
Classifier: Programming Language :: Python :: 3
Classifier: License :: OSI Approved :: MIT License
Classifier: Operating System :: OS Independent
Requires-Python: >=3.8
Requires-Dist: selenium>=4.24.0
Requires-Dist: pyautogui>=0.9.54
Requires-Dist: pynput>=1.8.1
Dynamic: author
Dynamic: author-email
Dynamic: classifier
Dynamic: description
Dynamic: description-content-type
Dynamic: home-page
Dynamic: requires-dist
Dynamic: requires-python
Dynamic: summary
